fastapi_fortify/__init__.py
fastapi_fortify/api/__init__.py
fastapi_fortify/api/management.py
fastapi_fortify/api/models.py
fastapi_fortify/config/__init__.py
fastapi_fortify/config/presets.py
fastapi_fortify/config/settings.py
fastapi_fortify/middleware/__init__.py
fastapi_fortify/middleware/rate_limiter.py
fastapi_fortify/middleware/security.py
fastapi_fortify/monitoring/__init__.py
fastapi_fortify/monitoring/auth_monitor.py
fastapi_fortify/monitoring/metrics.py
fastapi_fortify/protection/__init__.py
fastapi_fortify/protection/bot_detection.py
fastapi_fortify/protection/ip_blocklist.py
fastapi_fortify/protection/waf.py
fastapi_fortify/utils/__init__.py
fastapi_fortify/utils/decorators.py
fastapi_fortify/utils/ip_utils.py
fastapi_fortify/utils/security_utils.py
fastapi_fortify-1.0.1.dist-info/METADATA
fastapi_fortify-1.0.1.dist-info/WHEEL
fastapi_fortify-1.0.1.dist-info/licenses/LICENSE
fastapi_fortify-1.0.1.dist-info/RECORD
