Metadata-Version: 2.4
Name: fastapi-fortify
Version: 1.0.1
Summary: Comprehensive security middleware for FastAPI applications - WAF, rate limiting, bot detection, and more
Project-URL: Homepage, https://github.com/fastapi-fortify/fastapi-fortify
Project-URL: Documentation, https://github.com/fastapi-fortify/fastapi-fortify#readme
Project-URL: Repository, https://github.com/fastapi-fortify/fastapi-fortify
Project-URL: Issues, https://github.com/fastapi-fortify/fastapi-fortify/issues
Project-URL: Changelog, https://github.com/fastapi-fortify/fastapi-fortify/blob/main/CHANGELOG.md
Author-email: Your Name <your-email@example.com>
Maintainer-email: Your Name <your-email@example.com>
License: MIT License
License-File: LICENSE
Keywords: api-security,bot-detection,fastapi,middleware,rate-limiting,security,waf,web-security
Classifier: Development Status :: 4 - Beta
Classifier: Framework :: FastAPI
Classifier: Intended Audience :: Developers
Classifier: License :: OSI Approved :: MIT License
Classifier: Operating System :: OS Independent
Classifier: Programming Language :: Python :: 3
Classifier: Programming Language :: Python :: 3.8
Classifier: Programming Language :: Python :: 3.9
Classifier: Programming Language :: Python :: 3.10
Classifier: Programming Language :: Python :: 3.11
Classifier: Programming Language :: Python :: 3.12
Classifier: Topic :: Internet :: WWW/HTTP
Classifier: Topic :: Security
Classifier: Topic :: Software Development :: Libraries :: Python Modules
Classifier: Topic :: System :: Networking :: Firewalls
Requires-Python: >=3.8
Requires-Dist: fastapi>=0.68.0
Requires-Dist: httpx>=0.24.0
Requires-Dist: pydantic>=1.8.0
Requires-Dist: starlette>=0.14.0
Requires-Dist: user-agents>=2.2.0
Provides-Extra: all
Requires-Dist: black>=22.0.0; extra == 'all'
Requires-Dist: flake8>=4.0.0; extra == 'all'
Requires-Dist: geoip2>=4.0.0; extra == 'all'
Requires-Dist: httpx>=0.24.0; extra == 'all'
Requires-Dist: isort>=5.10.0; extra == 'all'
Requires-Dist: mkdocs-material>=8.0.0; extra == 'all'
Requires-Dist: mkdocs>=1.4.0; extra == 'all'
Requires-Dist: mkdocstrings[python]>=0.19.0; extra == 'all'
Requires-Dist: mypy>=0.991; extra == 'all'
Requires-Dist: pytest-asyncio>=0.21.0; extra == 'all'
Requires-Dist: pytest-cov>=4.0.0; extra == 'all'
Requires-Dist: pytest>=7.0.0; extra == 'all'
Requires-Dist: redis>=4.0.0; extra == 'all'
Requires-Dist: uvicorn>=0.18.0; extra == 'all'
Provides-Extra: dev
Requires-Dist: black>=22.0.0; extra == 'dev'
Requires-Dist: flake8>=4.0.0; extra == 'dev'
Requires-Dist: httpx>=0.24.0; extra == 'dev'
Requires-Dist: isort>=5.10.0; extra == 'dev'
Requires-Dist: mypy>=0.991; extra == 'dev'
Requires-Dist: pytest-asyncio>=0.21.0; extra == 'dev'
Requires-Dist: pytest-cov>=4.0.0; extra == 'dev'
Requires-Dist: pytest>=7.0.0; extra == 'dev'
Requires-Dist: uvicorn>=0.18.0; extra == 'dev'
Provides-Extra: docs
Requires-Dist: mkdocs-material>=8.0.0; extra == 'docs'
Requires-Dist: mkdocs>=1.4.0; extra == 'docs'
Requires-Dist: mkdocstrings[python]>=0.19.0; extra == 'docs'
Provides-Extra: geoip
Requires-Dist: geoip2>=4.0.0; extra == 'geoip'
Provides-Extra: redis
Requires-Dist: redis>=4.0.0; extra == 'redis'
